functions_by_krinatova/README.md
functions_by_krinatova/math_functions.py
functions_by_krinatova-0.3.0.dist-info/WHEEL
functions_by_krinatova-0.3.0.dist-info/METADATA
functions_by_krinatova-0.3.0.dist-info/RECORD
