Metadata-Version: 2.1
Name: functions-by-krinatova
Version: 0.3.0
Summary: This is our test project
Author: Kanykei Rinatova
Author-email: krdevops22@gmail.com
Requires-Python: >=3.10,<4.0
Classifier: Programming Language :: Python :: 3
Classifier: Programming Language :: Python :: 3.10
Classifier: Programming Language :: Python :: 3.11
